MANIFEST.in
README.md
setup.py
requirements/pkg.txt
test/__init__.py
test/unit/__init__.py
test/unit/extractors/__init__.py
test/unit/extractors/test_csv_extractor.py
test/unit/extractors/test_excel_extractor.py
test/unit/extractors/test_extractor.py
test/unit/loaders/__init__.py
test/unit/loaders/test_loader.py
test/unit/loaders/postgres/__init__.py
test/unit/loaders/postgres/test_postgres_loader.py
test/unit/loaders/postgres/test_postgres_no_relationships.py
test/unit/loaders/postgres/test_postgres_one_relationships.py
wextractor/__init__.py
wextractor.egg-info/PKG-INFO
wextractor.egg-info/SOURCES.txt
wextractor.egg-info/dependency_links.txt
wextractor.egg-info/requires.txt
wextractor.egg-info/top_level.txt
wextractor/extractors/__init__.py
wextractor/extractors/csv_extractor.py
wextractor/extractors/excel_extractor.py
wextractor/extractors/extractor.py
wextractor/loaders/__init__.py
wextractor/loaders/loader.py
wextractor/loaders/postgres.py