Metadata-Version: 1.1
Name: wextractor
Version: 0.1.dev4
Summary: Extract flat data and load it as relational data
Home-page: https://github.com/codeforamerica/w-drive-extractor
Author: Ben Smithgall
Author-email: bsmithgall@codeforamerica.org
License: MIT
Platform: UNKNOWN
Classifier: Development Status :: 3 - Alpha
Classifier: Programming Language :: Python :: 2
Classifier: Programming Language :: Python :: 2.6
Classifier: Programming Language :: Python :: 2.7
Classifier: Intended Audience :: Developers
Classifier: Topic :: Software Development :: Libraries :: Python Modules
